econuker/Exceptions.py
econuker/__init__.py
econuker/async_client.py
econuker/client.py
econuker-1.0.9.dist-info/METADATA
econuker-1.0.9.dist-info/WHEEL
econuker-1.0.9.dist-info/top_level.txt
econuker-1.0.9.dist-info/RECORD
